LICENSE
MANIFEST.in
README.md
setup.py
watcard.py
watcard.egg-info/PKG-INFO
watcard.egg-info/SOURCES.txt
watcard.egg-info/dependency_links.txt
watcard.egg-info/requires.txt
watcard.egg-info/top_level.txt