Metadata-Version: 1.0
Name: watcard
Version: 0.1.0
Summary: Work with transaction and balance data from University of Waterloo's Watcard
Home-page: https://github.com/aibram/watcard
Author: Ansis Brammanis
Author-email: ansis.brammanis@gmail.com
License: MIT
Download-URL: https://github.com/aibram/watcard/tarball/master
Platform: UNKNOWN
Classifier: Development Status :: 3 - Alpha
Classifier: Intended Audience :: Developers
Classifier: License :: OSI Approved :: MIT License
Classifier: Programming Language :: Python
Classifier: Programming Language :: Python :: 2.6
Classifier: Programming Language :: Python :: 2.7
